Workbook

Sheet Santo Design Trial Balance 2025
A2: Santo Design
A3: Adjusted Trial Balance
A4: December 31, 2025
C6: Dr. | E6: Cr.
A7: Cash | C7: 11350
A8: Accounts Receivable | C8: 21500
A9: Supplies | C9: 5000
A10: Prepaid Insurance | C10: 2500
A11: Equipment | C11: 60000
A12: Accumulted Depreciation - Equipment | E12: 35000
A13: Accounts Payable | E13: 5000
A14: Interest Payable | E14: 150
A15: Notes Payable | E15: 5000
A16: Unearned Service Revenue | E16: 5600
A17: Salaries and Wages Payable | E17: 1300
A18: Common Stock | E18: 10000
A19: Retained Earnings | E19: 3500
A20: Service Revenue | E20: 61500
A21: Salaries and Wages Expense | C21: 11300
A22: Insurance Expense | C22: 850
A23: Interest Expense | C23: 150
A24: Depreciation Expense | C24: 7000
A25: Supplies Expense | C25: 3400
A26: Rent Expense | C26: 4000
C27: =SUM(C7:C26) -> 127050 | E27: =SUM(E7:E26) -> 127050

Sheet Santo Design Income Statement
A2: Santo Design
A3: Income Statement
A4: For the Year Ended December 31, 2025
A7: Revenues
A8: Service revenue | D8: ='Santo Design Trial Balance 2025'!E20 -> 61500
A10: Expenses
A11: Salaries and Wages Expense | B11: ='Santo Design Trial Balance 2025'!C21 -> 11300
A12: Insurance Expense | B12: ='Santo Design Trial Balance 2025'!C22 -> 850
A13: Interest Expense | B13: ='Santo Design Trial Balance 2025'!C23 -> 150
A14: Depreciation Expense | B14: ='Santo Design Trial Balance 2025'!C24 -> 7000
A15: Supplies Expense | B15: ='Santo Design Trial Balance 2025'!C25 -> 3400
A16: Rent Expense | B16: ='Santo Design Trial Balance 2025'!C26 -> 4000
A18: Total expenses | D18: =SUM(B11:B16) -> 26700
A20: Net income | D20: =D8-D18 -> 34800

Sheet Santo Design Retained Earnings
A2: Santo Design
A3: Retained Earnings Statement
A4: For the Year Ended December 31, 2025
A7: Retained earnings, January 1, as reported | D7: ='Santo Design Trial Balance 2025'!E19 -> 3500
A8: Add: Net income | D8: ='Santo Design Income Statement'!D20 -> 34800
A9: Retained earnings, December 31 | D9: =D7+D8 -> 38300

Sheet Santo Design Balance Sheet
A2: Santo Design
A3: Balance Sheet
A4: As of December 31, 2025
A7: Assets
A8: Cash | D8: ='Santo Design Trial Balance 2025'!C7 -> 11350
A9: Accounts Receivable | D9: ='Santo Design Trial Balance 2025'!C8 -> 21500
A10: Supplies | D10: ='Santo Design Trial Balance 2025'!C9 -> 5000
A11: Prepaid Insurance | D11: ='Santo Design Trial Balance 2025'!C10 -> 2500
A12: Equipment | B12: ='Santo Design Trial Balance 2025'!C11 -> 60000
A13: Less: Accumulted Depreciation - Equipment | B13: =-'Santo Design Trial Balance 2025'!E12 -> -35000 | D13: =SUM(B12:B13) -> 25000
A15: Total Assets | D15: =SUM(D8:D13) -> 65350
A17: Liabilities
A18: ='Santo Design Trial Balance 2025'!A13 -> Accounts Payable | D18: ='Santo Design Trial Balance 2025'!E13 -> 5000
A19: ='Santo Design Trial Balance 2025'!A14 -> Interest Payable | D19: ='Santo Design Trial Balance 2025'!E14 -> 150
A20: ='Santo Design Trial Balance 2025'!A15 -> Notes Payable | D20: ='Santo Design Trial Balance 2025'!E15 -> 5000
A21: ='Santo Design Trial Balance 2025'!A16 -> Unearned Service Revenue | D21: ='Santo Design Trial Balance 2025'!E16 -> 5600
A22: ='Santo Design Trial Balance 2025'!A17 -> Salaries and Wages Payable | D22: ='Santo Design Trial Balance 2025'!E17 -> 1300
A24: Total Liabilities | D24: =SUM(D18:D23) -> 17050
A26: Stockholders' Equity
A27: ='Santo Design Trial Balance 2025'!A18 -> Common Stock | D27: ='Santo Design Trial Balance 2025'!E18 -> 10000
A28: ='Santo Design Trial Balance 2025'!A19 -> Retained Earnings | D28: ='Santo Design Retained Earnings'!D9 -> 38300
A30: Total Stockholders' Equity | D30: =SUM(D27:D29) -> 48300
A32: Total Liabilities and Stockholders' Equity | D32: =D24+D30 -> 65350
D34: =D15-D32 -> 0
